pdf_section_binding/__init__.py
pdf_section_binding/cli.py
pdf_section_binding/core.py
pdf_section_binding/version.py
pdf_section_binding-1.0.1.dist-info/licenses/LICENSE
pdf_section_binding-1.0.1.dist-info/METADATA
pdf_section_binding-1.0.1.dist-info/WHEEL
pdf_section_binding-1.0.1.dist-info/entry_points.txt
pdf_section_binding-1.0.1.dist-info/top_level.txt
pdf_section_binding-1.0.1.dist-info/RECORD
