Metadata-Version: 2.4
Name: pdf-section-binding
Version: 1.0.1
Summary: A CLI tool for reordering PDF pages for section binding (bookbinding)
Home-page: https://github.com/sravankumarrekandar/pdf-section-binding
Author: Sravan Kumar Rekandar
Author-email: Sravan Kumar Rekandar <sravankumarrekandar@example.com>
License-Expression: MIT
Project-URL: Homepage, https://github.com/yourusername/pdf-section-binding
Project-URL: Bug Reports, https://github.com/yourusername/pdf-section-binding/issues
Project-URL: Source, https://github.com/yourusername/pdf-section-binding
Project-URL: Documentation, https://github.com/yourusername/pdf-section-binding#readme
Keywords: pdf,bookbinding,section-binding,printing,cli,page-reordering,signatures,folding
Classifier: Development Status :: 4 - Beta
Classifier: Intended Audience :: End Users/Desktop
Classifier: Intended Audience :: Developers
Classifier: Topic :: Multimedia :: Graphics :: Graphics Conversion
Classifier: Topic :: Printing
Classifier: Topic :: Utilities
Classifier: Programming Language :: Python :: 3
Classifier: Programming Language :: Python :: 3.7
Classifier: Programming Language :: Python :: 3.8
Classifier: Programming Language :: Python :: 3.9
Classifier: Programming Language :: Python :: 3.10
Classifier: Programming Language :: Python :: 3.11
Classifier: Programming Language :: Python :: 3.12
Classifier: Operating System :: OS Independent
Classifier: Environment :: Console
Requires-Python: >=3.7
License-File: LICENSE
Requires-Dist: PyPDF2>=3.0.0
Provides-Extra: dev
Requires-Dist: pytest>=7.0.0; extra == "dev"
Requires-Dist: pytest-cov>=4.0.0; extra == "dev"
Requires-Dist: black>=22.0.0; extra == "dev"
Requires-Dist: flake8>=5.0.0; extra == "dev"
Requires-Dist: mypy>=1.0.0; extra == "dev"
Provides-Extra: test
Requires-Dist: pytest>=7.0.0; extra == "test"
Requires-Dist: pytest-cov>=4.0.0; extra == "test"
Dynamic: author
Dynamic: home-page
Dynamic: license-file
Dynamic: requires-python
